area4/__init__.py
area4/dividers.txt
area4/util.py
area4-3.11.0.dist-info/LICENSE
area4-3.11.0.dist-info/METADATA
area4-3.11.0.dist-info/WHEEL
area4-3.11.0.dist-info/top_level.txt
area4-3.11.0.dist-info/RECORD
